Workbook
Name aporte: 'Projeto Valéria'!$D$17
Name patrimonio: 'Projeto Valéria'!$D$20
Name qtd_anos: 'Projeto Valéria'!$D$18
Name rendimento_carteira: 'Projeto Valéria'!$D$13
Name salario: 'Projeto Valéria'!$D$12
Name sugestao_investimento: 'Projeto Valéria'!$D$14
Name taxa_mensal: 'Projeto Valéria'!$D$19

Sheet Projeto Valéria
B11: CONFIGURAÇÕES
B12: Salario | D12: 5000
B13: Rendimentos Carteira | D13: 0.006
B14: Sugestão de Investimento(30%) | D14: =D12*30% -> 1500
B16: INVESTIMENTOS MENSAL
B17: Quanto investir por mes? | D17: 750
B18: Por quanto anos? | D18: 5
B19: Taxa de rendimento mensal? | D19: 0.0108
B20: Patrimônio acumulado? | D20: =FV(taxa_mensal,qtd_anos*12,aporte*-1) -> 62853.015
B21: Dividendos mensais? | D21: =patrimonio*rendimento_carteira -> 377.11809
B23: Cenários | D23: Dividendo
A24: 2 | B24: Quanto em 2 anos? | C24: =FV($D$19,A$24*12,$D$17*-1) -> 20423.148 | D24: =C24*rendimento_carteira -> 122.53889
A25: 5 | B25: Quanto em 5 anos? | C25: =FV($D$19,A$25*12,$D$17*-1) -> 62853.015 | D25: =C25*rendimento_carteira -> 377.11809
A26: 10 | B26: Quanto em 10 anos? | C26: =FV($D$19,A$26*12,$D$17*-1) -> 182593.25 | D26: =C26*rendimento_carteira -> 1095.5595
A27: 20 | B27: Quanto em 20 anos? | C27: =FV($D$19,A$27*12,$D$17*-1) -> 845286.74 | D27: =C27*rendimento_carteira -> 5071.7205
A28: 30 | B28: Quanto em 30 anos? | C28: =FV($D$19,A$28*12,$D$17*-1) -> 3250428.6 | D28: =C28*rendimento_carteira -> 19502.572
B31: PERFIL | C31: Moderado
B32: Valor a ser investido por mês | C32: =aporte -> 750
B33: Tipo de FII | C33: Percentual Sugerido | D33: Valores
B34: PAPEL | C34: =VLOOKUP($C$31&"-"&B34,Planilha2!$A:$D,4,) -> 0.32 | D34: =C34*$C$32 -> 240
B35: TIJOLOS | C35: =VLOOKUP($C$31&"-"&B35,Planilha2!$A:$D,4,) -> 0.35 | D35: =C35*$C$32 -> 262.5
B36: HIBRIDOS | C36: =VLOOKUP($C$31&"-"&B36,Planilha2!$A:$D,4,) -> 0.08 | D36: =C36*$C$32 -> 60
B37: FOFs | C37: =VLOOKUP($C$31&"-"&B37,Planilha2!$A:$D,4,) -> 0.05 | D37: =C37*$C$32 -> 37.5
B38: DESENVOLVIMENTO | C38: =VLOOKUP($C$31&"-"&B38,Planilha2!$A:$D,4,) -> 0.1 | D38: =C38*$C$32 -> 75
B39: HOTELARIAS | C39: =VLOOKUP($C$31&"-"&B39,Planilha2!$A:$D,4,) -> 0.1 | D39: =C39*$C$32 -> 75
D40: =SUM(D34:D39) -> 750

Sheet Planilha2
A1: Chave | B1: PERFIL | C1: TIPO DE FII | D1: %
A2: =B2&"-"&C2 -> Conservador-PAPEL | B2: Conservador | C2: PAPEL | D2: 0.3
A3: =B3&"-"&C3 -> Conservador-TIJOLOS | B3: Conservador | C3: TIJOLOS | D3: 0.5 | J3: %
A4: =B4&"-"&C4 -> Conservador-HIBRIDOS | B4: Conservador | C4: HIBRIDOS | D4: 0.1 | H4: Moderado-TIJOLOS | J4: =VLOOKUP(H4,$A:$D,4,) -> 0.35
A5: =B5&"-"&C5 -> Conservador-FOFs | B5: Conservador | C5: FOFs | D5: 0.1
A6: =B6&"-"&C6 -> Conservador-DESENVOLVIMENTO | B6: Conservador | C6: DESENVOLVIMENTO | D6: 0
A7: =B7&"-"&C7 -> Conservador-HOTELARIAS | B7: Conservador | C7: HOTELARIAS | D7: 0
A8: =B8&"-"&C8 -> Moderado-PAPEL | B8: Moderado | C8: PAPEL | D8: 0.32
A9: =B9&"-"&C9 -> Moderado-TIJOLOS | B9: Moderado | C9: TIJOLOS | D9: 0.35
A10: =B10&"-"&C10 -> Moderado-HIBRIDOS | B10: Moderado | C10: HIBRIDOS | D10: 0.08
A11: =B11&"-"&C11 -> Moderado-FOFs | B11: Moderado | C11: FOFs | D11: 0.05
A12: =B12&"-"&C12 -> Moderado-DESENVOLVIMENTO | B12: Moderado | C12: DESENVOLVIMENTO | D12: 0.1
A13: =B13&"-"&C13 -> Moderado-HOTELARIAS | B13: Moderado | C13: HOTELARIAS | D13: 0.1
A14: =B14&"-"&C14 -> Agressivo-PAPEL | B14: Agressivo | C14: PAPEL | D14: 0.5
A15: =B15&"-"&C15 -> Agressivo-TIJOLOS | B15: Agressivo | C15: TIJOLOS | D15: 0.1
A16: =B16&"-"&C16 -> Agressivo-HIBRIDOS | B16: Agressivo | C16: HIBRIDOS | D16: 0.05
... A19: =B19&"-"&C19 -> Agressivo-HOTELARIAS | B19: Agressivo | C19: HOTELARIAS | D19: 0.1
